bgpneiget/__init__.py
bgpneiget/cli.py
bgpneiget/device/__init__.py
bgpneiget/device/arista.py
bgpneiget/device/base.py
bgpneiget/device/cisco_iosxe.py
bgpneiget/device/cisco_iosxr.py
bgpneiget/device/cisco_nxos.py
bgpneiget/device/juniper.py
bgpneiget/devices.py
bgpneiget/runcmds.py
bgpneiget/textfsm/cisco_iosxe_show_bgp.textfsm
bgpneiget/textfsm/cisco_iosxe_show_bgp_vrf.textfsm
bgpneiget/textfsm/cisco_iosxr_show_bgp.textfsm
bgpneiget/worker.py
bgpneiget-2.0.18.dist-info/LICENSE
bgpneiget-2.0.18.dist-info/METADATA
bgpneiget-2.0.18.dist-info/WHEEL
bgpneiget-2.0.18.dist-info/entry_points.txt
bgpneiget-2.0.18.dist-info/RECORD
