Metadata-Version: 2.3
Name: bgpneiget
Version: 2.0.18
Summary: Get BGP Neighbours from network devices
License: BSD-2-Clause
Author: Rob Woodward
Author-email: rob@emailplus.org
Requires-Python: >=3.10,<4.0
Classifier: License :: OSI Approved :: BSD License
Classifier: Programming Language :: Python :: 3
Classifier: Programming Language :: Python :: 3.10
Classifier: Programming Language :: Python :: 3.11
Classifier: Programming Language :: Python :: 3.12
Classifier: Programming Language :: Python :: 3.13
Requires-Dist: aiosqlite (>=0.21.0,<0.22.0)
Requires-Dist: asyncssh (>=2.13.1,<3.0.0)
Requires-Dist: click (>=8.1.3,<9.0.0)
Requires-Dist: scrapli (==2024.1.30)
Requires-Dist: textfsm (>=1.1.3,<2.0.0)
Requires-Dist: xmltodict (>=0.14.0,<0.15.0)
Project-URL: Repository, https://github.com/robwdwd/bgpneiget
